discord_bot_maker/__init__.py
discord_bot_maker/command.py
discord_bot_maker/dbot.py
discord_bot_maker/example.py
discord_bot_maker-1.0.0.dist-info/LICENSE
discord_bot_maker-1.0.0.dist-info/METADATA
discord_bot_maker-1.0.0.dist-info/WHEEL
discord_bot_maker-1.0.0.dist-info/top_level.txt
discord_bot_maker-1.0.0.dist-info/RECORD
