Metadata-Version: 2.1
Name: discord_bot_maker
Version: 1.0.0
Summary: A Python Package to make Discord bots with ease. (It also has a lot of documentation so you will never be stuck)
Home-page: https://github.com/dehadeaaryan/discord-bot-maker
Author: Aaryan Dehade
Author-email: dehadeaaryan@gmail.com
License: UNKNOWN
Project-URL: Bug Tracker, https://github.com/dehadeaaryan/discord-bot-maker/issues
Platform: UNKNOWN
Classifier: Programming Language :: Python :: 3
Classifier: License :: OSI Approved :: MIT License
Classifier: Operating System :: OS Independent
Requires-Python: >=3.6
License-File: LICENSE
